<Properties StartupConfiguration="{0EEBF18E-272D-828E-0FE3-FE5D1E52DE1C}|">
  <MonoDevelop.Ide.Workbench ActiveDocument="Assets/Scripts/PlayerController.cs">
    <Files>
      <File FileName="Assets/Test/TestScript/EnemyController.cs" Line="72" Column="14" />
      <File FileName="Assets/Scripts/CardData.cs" Line="43" Column="6" />
      <File FileName="Assets/Scripts/CardClickHandler.cs" Line="6" Column="1" />
      <File FileName="Assets/Scripts/EnemyController.cs" Line="39" Column="10" />
      <File FileName="Assets/Scripts/GameManager.cs" Line="48" Column="1" />
      <File FileName="Assets/Scripts/PlayerController.cs" Line="22" Column="51" />
      <File FileName="Assets/Scripts/BattleManager.cs" Line="37" Column="1" />
      <File FileName="Assets/Scripts/DeckManager.cs" Line="30" Column="77" />
      <File FileName="Assets/Scripts/ZoneHandler.cs" Line="22" Column="40" />
    </Files>
    <Pads>
      <Pad Id="ProjectPad">
        <State name="__root__">
          <Node name="CardGame" expanded="True">
            <Node name="Assets" expanded="True">
              <Node name="Scripts" expanded="True">
                <Node name="PlayerController.cs" selected="True" />
              </Node>
            </Node>
          </Node>
        </State>
      </Pad>
    </Pads>
  </MonoDevelop.Ide.Workbench>
  <MonoDevelop.Ide.DebuggingService.PinnedWatches />
  <MonoDevelop.Ide.Workspace ActiveConfiguration="Debug" />
  <MonoDevelop.Ide.ItemProperties.Assembly-CSharp PreferredExecutionTarget="9c24f7e0-1b05-40c9-ae5f-873cf612d520" />
  <MonoDevelop.Ide.DebuggingService.Breakpoints>
    <BreakpointStore />
  </MonoDevelop.Ide.DebuggingService.Breakpoints>
  <MultiItemStartupConfigurations />
</Properties>